ben_package_test/__init__.py
ben_package_test/skeleton.py
ben_package_test-0.1.0.dist-info/LICENSE.txt
ben_package_test-0.1.0.dist-info/METADATA
ben_package_test-0.1.0.dist-info/WHEEL
ben_package_test-0.1.0.dist-info/top_level.txt
ben_package_test-0.1.0.dist-info/RECORD
