Metadata-Version: 2.1
Name: ben_package_test
Version: 0.1.0
Summary: Add a short description here!
Home-page: https://github.com/pyscaffold/ben_package_test/
Author: Ben-unbelieveable
Author-email: 614347533@qq.com
License: MIT
Project-URL: Documentation, https://pyscaffold.org/
Platform: any
Classifier: Development Status :: 4 - Beta
Classifier: Programming Language :: Python
License-File: LICENSE.txt
Requires-Dist: importlib-metadata ; python_version < "3.8"
Provides-Extra: testing
Requires-Dist: setuptools ; extra == 'testing'
Requires-Dist: pytest ; extra == 'testing'
Requires-Dist: pytest-cov ; extra == 'testing'
